clockGenAndDist/prereq/counter.v
/* Design of Synchronous up  counter */

// parameter is a keyword that is used to define the constants
// # (parameter <variable_name> = <value>), where # is a processor directive
module counter #( parameter WIDTH = 4)(
				       input wire  clk,
				       input wire  rst,
				       input wire  enable,
				       output reg[WIDTH-1:0] count
				       );
   always @(posedge clk or posedge rst) begin
      if(rst)
	count <= 0;
      else if (enable)
	count <= count+1;   
   end
endmodule // counter

clockGenAndDist/prereq/counter/counter_tb.v
/* Testbench for counter module  */
/*
  Design Engineer : Janani P Srinivasan
  Design Name : Testbench for 4 bit synchronous upcounter  
*/



`timescale 1ns/1ps
module counter_tb();
   reg clk;
   reg enable ;
   reg rst;
   wire [3:0] count;

   counter #(.WIDTH(4)) uut (
			   .clk(clk),
			   .rst(rst),
			   .enable(enable),
			   .count(count)
			   );
   always #5 clk = ~clk;
   initial begin
      $dumpfile("counter_tb.vcd");
      $dumpvars(0,counter_tb);
      //Initiate signals      
      clk = 0;
      enable =0;
      rst = 1;
      //reset is 1 here, the counter will be reset to 0

      #10;
      rst = 0;
      enable =1;
      #200;
      enable=0;
      #20;
      rst=1;
      enable=1;
      #40;
      rst=0;
      enable = 0;
      #10;
      rst = 1;
      enable =1;
      #10;
      
      rst =0;
      $finish;
          
     
   end
endmodule // counter_tb

clockGenAndDist/prereq/counter/counter_tb.vcd
$date
	Fri Apr  4 22:22:01 2025
$end
$version
	Icarus Verilog
$end
$timescale
	1ps
$end
$scope module counter_tb $end
$var wire 4 ! count [3:0] $end
$var reg 1 " clk $end
$var reg 1 # enable $end
$var reg 1 $ rst $end
$scope module uut $end
$var wire 1 " clk $end
$var wire 1 # enable $end
$var wire 1 $ rst $end
$var reg 4 % count [3:0] $end
$upscope $end
$upscope $end
$enddefinitions $end
#0
$dumpvars
b0 %
1$
0#
0"
b0 !
$end
#5000
1"
#10000
0"
1#
0$
#15000
b1 !
b1 %
1"
#20000
0"
#25000
b10 !
b10 %
1"
#30000
0"
#35000
b11 !
b11 %
1"
#40000
0"
#45000
b100 !
b100 %
1"
#50000
0"
#55000
b101 !
b101 %
1"
#60000
0"
#65000
b110 !
b110 %
1"
#70000
0"
#75000
b111 !
b111 %
1"
#80000
0"
#85000
b1000 !
b1000 %
1"
#90000
0"
#95000
b1001 !
b1001 %
1"
#100000
0"
#105000
b1010 !
b1010 %
1"
#110000
0"
#115000
b1011 !
b1011 %
1"
#120000
0"
#125000
b1100 !
b1100 %
1"
#130000
0"
#135000
b1101 !
b1101 %
1"
#140000
0"
#145000
b1110 !
b1110 %
1"
#150000
0"
#155000
b1111 !
b1111 %
1"
#160000
0"
#165000
b0 !
b0 %
1"
#170000
0"
#175000
b1 !
b1 %
1"
#180000
0"
#185000
b10 !
b10 %
1"
#190000
0"
#195000
b11 !
b11 %
1"
#200000
0"
#205000
b100 !
b100 %
1"
#210000
0"
0#
#215000
1"
#220000
0"
#225000
1"
#230000
b0 !
b0 %
0"
1#
1$
#235000
1"
#240000
0"
#245000
1"
#250000
0"
#255000
1"
#260000
0"
#265000
1"
#270000
0"
0#
0$
#275000
1"
#280000
0"
1#
1$
#285000
1"
#290000
0"
0$
