sequentialCircuits/latchesAndFlipflop/latch/dlatch.v
`timescale 1ns / 1ns

module dlatch (
    input wire en,
    input wire d,
    output q,
    output  qbar
);
    reg latch;
    always @ (*) begin
        if (en)
            latch<=d;
    end

    assign q = latch;
    assign qbar = ~q;


    
endmodule

sequentialCircuits/latchesAndFlipflop/latch/dlatch_tb.v
`timescale 1ns/1ns

module dlatch_tb();
    
    // Initiate the testbench variables
    reg d;
    reg en;
    wire q;
    wire qbar;

    // Instantiate the uut
    dlatch uut(
        .d (d),
        .en (en),
        .q(q),
        .qbar(qbar)
    );

    //Create Stimulus

    initial begin
        $monitor ($time , "\t en = %b, d = %b ,q = %b ,qbar = %b",en,d,q,qbar);
        en=0; d=0;
        #1; d =0;
        #1; d = 1;
        #1.5; en =1;
        #0.2;d=0;
        #0.3;d=1;
        #1;en=0;d=0;
        #1;en=1;d=1;
        #2;d=0;
        #1;en=0;
        #1;d=1;
    end

    initial begin
        #10 $finish;
    end

    initial begin
        $dumpfile("wave.vcd");
        $dumpvars(0, dlatch_tb);
    end

endmodule

sequentialCircuits/latchesAndFlipflop/latch/wave.vcd
$date
	Fri Jun 27 17:52:31 2025
$end
$version
	Icarus Verilog
$end
$timescale
	1ns
$end
$scope module dlatch_tb $end
$var wire 1 ! qbar $end
$var wire 1 " q $end
$var reg 1 # d $end
$var reg 1 $ en $end
$scope module uut $end
$var wire 1 # d $end
$var wire 1 $ en $end
$var wire 1 " q $end
$var wire 1 ! qbar $end
$var reg 1 " latch $end
$upscope $end
$upscope $end
$enddefinitions $end
$comment Show the parameter values. $end
$dumpall
$end
#0
$dumpvars
0$
0#
x"
x!
$end
#2
1#
#4
0!
1"
1#
1$
#5
0#
0$
#6
1#
1$
#8
1!
0"
0#
#9
0$
#10
1#
