sequentialCircuits/latchesAndFlipflop/ff/dff_syn.v
module dff_syn(
    input wire clk,
    input wire rst,
    input d,
    output reg q,
    output wire qbar
);

always @(posedge clk) begin
    if (!rst)
        q <= 1'b0;
    else 
        q <= d;    
end
assign qbar = ~q;
endmodule

sequentialCircuits/latchesAndFlipflop/ff/dff_syn_tb.v
`timescale 1ns/1ps 

module dff_syn_tb();
    reg clk = 0;
    reg rst;
    reg d;
    wire q;
    wire qbar;

// Initiate a delay variable in the input
// a random delay is pauses the toggling input for a while
// in realtime, the data does not change instantaneously. 

    reg [3:1] delay;
    integer i; 

    dff_syn uut (
        .clk(clk),
        .rst(rst),
        .d(d),
        .q(q),
        .qbar(qbar)
    );

    // create the clock signal.

    always begin
        #0.5 clk = ~clk;    
    end

    initial begin
        // the data is also zero and the reset is also 0;
        // !rst is 1. meaning reset is high and the data cannot be propogated to q
        rst = 0;
        d = 0;
        for (i=0;i<4;i++) begin
            delay = $urandom_range(1,3);
            //a random delay is being generated.
            // after a random delay of some seconds, we flip the d
            // so instead of hardcoding the value of d in every cycle, we randomly flip after a time
            #(delay) d = ~d;
        end

        rst =1;
        //!rst is pulled to zero
        // the value of d is propogated to q
        for (i = 0; i<4;i++) begin
            delay = $urandom_range(1,3);
            #(delay) d = ~d;
        end 

        // now setting some value for d
        d =1'b1;
        #(2);
        rst = 0;        
    end



    initial begin
    $dumpfile("dff.vcd");   // name of the waveform output file
    $dumpvars(0, dff_syn_tb);  // dump all variables in the testbench hierarchy
    #50 $finish;
    end

endmodule

sequentialCircuits/latchesAndFlipflop/ff/dff.vcd
$date
	Wed Jul 09 15:57:44 2025
$end
$version
	Icarus Verilog
$end
$timescale
	1ps
$end
$scope module dff_syn_tb $end
$var wire 1 ! qbar $end
$var wire 1 " q $end
$var reg 1 # clk $end
$var reg 1 $ d $end
$var reg 3 % delay [3:1] $end
$var reg 1 & rst $end
$var integer 32 ' i [31:0] $end
$scope module uut $end
$var wire 1 # clk $end
$var wire 1 $ d $end
$var wire 1 ! qbar $end
$var wire 1 & rst $end
$var reg 1 " q $end
$upscope $end
$upscope $end
$enddefinitions $end
$comment Show the parameter values. $end
$dumpall
$end
#0
$dumpvars
b0 '
0&
b10 %
0$
0#
x"
x!
$end
#500
1!
0"
1#
#1000
0#
#1500
1#
#2000
0#
b1 %
b1 '
1$
#2500
1#
#3000
0#
b10 '
0$
#3500
1#
#4000
0#
b11 '
1$
#4500
1#
#5000
0#
b10 %
1&
b0 '
0$
#5500
1#
#6000
0#
#6500
1#
#7000
0#
b11 %
b1 '
1$
#7500
0!
1"
1#
#8000
0#
#8500
1#
#9000
0#
#9500
1#
#10000
0#
b1 %
b10 '
0$
#10500
1!
0"
1#
#11000
0#
b11 '
1$
#11500
0!
1"
1#
#12000
0#
b100 '
1$
#12500
1#
#13000
0#
#13500
1#
#14000
0#
0&
#14500
1!
0"
1#
