sequentialCircuits/shift_regs/pipo_reg.v
module pipo_reg(
    input clk,
    input rst,
    input [3:0] d,
    output reg [3:0]q
);
    always @(posedge clk or negedge rst) begin
        if (!rst) 
            q <= 4'b0000;
        else
            q <= d;

    end

endmodule

sequentialCircuits/shift_regs/pipo_reg_tb.v
`timescale 1ns/1ps

module pipo_reg_tb();
    reg clk =0;
    reg rst;
    reg [3:0] d;
    wire [3:0] q;
    reg [1:0] delay;
    integer i;

    pipo_reg uut (
        .clk(clk),
        .d(d),
        .rst(rst),
        .q(q)
    );

    always begin
    #0.5 clk = ~clk;

    end

    initial begin 
    
    rst = 0; d =0;
    for (i=0;i<4;i++) begin
        delay = $urandom_range(1,3);
        #(delay) d = ~d;
    end
    rst = 1; 
    for (i=0;i<4;i++) begin
        delay = $urandom_range(1,3);
        #(delay) d = ~d;
    end

    end

    initial begin
        $dumpfile("wave.vcd");
        $dumpvars(0,pipo_reg_tb);
        #40 $finish;
    end

endmodule

sequentialCircuits/shift_regs/pipo/wave.vcd
$date
	Wed Jul 09 18:17:44 2025
$end
$version
	Icarus Verilog
$end
$timescale
	1ps
$end
$scope module pipo_reg_tb $end
$var wire 4 ! q [3:0] $end
$var reg 1 " clk $end
$var reg 4 # d [3:0] $end
$var reg 2 $ delay [1:0] $end
$var reg 1 % rst $end
$var integer 32 & i [31:0] $end
$scope module uut $end
$var wire 1 " clk $end
$var wire 4 ' d [3:0] $end
$var wire 1 % rst $end
$var reg 4 ( q [3:0] $end
$upscope $end
$upscope $end
$enddefinitions $end
$comment Show the parameter values. $end
$dumpall
$end
#0
$dumpvars
b0 (
b0 '
b0 &
0%
b10 $
b0 #
0"
b0 !
$end
#500
1"
#1000
0"
#1500
1"
#2000
0"
b1 $
b1 &
b1111 #
b1111 '
#2500
1"
#3000
0"
b10 &
b0 #
b0 '
#3500
1"
#4000
0"
b11 &
b1111 #
b1111 '
#4500
1"
#5000
0"
b10 $
1%
b0 &
b0 #
b0 '
#5500
1"
#6000
0"
#6500
1"
#7000
0"
b11 $
b1 &
b1111 #
b1111 '
#7500
b1111 !
b1111 (
1"
#8000
0"
#8500
1"
#9000
0"
#9500
1"
#10000
0"
b1 $
b10 &
b0 #
b0 '
#10500
b0 !
b0 (
1"
#11000
0"
b11 &
b1111 #
b1111 '
#11500
b1111 !
b1111 (
1"
#12000
0"
b100 &
b0 #
b0 '
#12500
b0 !
b0 (
1"
