sequentialCircuits/shift_regs/siso/shift_reg_siso.v
module shift_reg_siso(
	input reset_n,
	input clk,
    input sdi, // serial data in
	output sdo // serial data out
    );
	
	// Internal 4 bits wide register
	reg [3:0] siso;
	
	// Async negative reset is used
	// The input data is the same as the output data
	always @(posedge clk or negedge reset_n) begin
	    if (!reset_n)
		    siso <= 4'b0;
	    else
		    siso[3:0] <= {siso[2:0], sdi};
	end

    // Connect the sdo net to the register MSB
    assign sdo = siso[3];

endmodule

sequentialCircuits/shift_regs/siso/tb_shift_reg_siso.v

`timescale 1us/1ns
module tb_shift_reg_siso();
	
	// Testbench variables
    reg sdi;
	reg clk = 0;
	reg reset_n;
	wire sdo;
	
	// Instantiate the DUT
    shift_reg_siso SISO0(
		.reset_n(reset_n),
	    .clk    (clk    ),
        .sdi    (sdi    ),
	    .sdo    (sdo    )
    );
	
	// Create the clock signal
	always begin #0.5 clk = ~clk; end
	
    // Create stimulus	  
    initial begin
    	sdi = 0;
    	reset_n = 0; 
    	#1.3; 
    	reset_n = 1;

    	sdi = 1; @(posedge clk); // Clock 1: shift in '1'
    	sdi = 0; @(posedge clk); // Clock 2: shift in '0'
    	sdi = 1; @(posedge clk); // Clock 3: shift in '1'
    	sdi = 0; @(posedge clk); // Clock 4: shift in '0'
	end
	
    // This will stop the simulator when the time expires
    initial begin
		$dumpfile("wave.vcd");
        $dumpvars(0,tb_shift_reg_siso);
        #40 $finish;
    end  
endmodule

sequentialCircuits/shift_regs/siso/wave.vcd
$date
	Sun Jul 13 12:41:42 2025
$end
$version
	Icarus Verilog
$end
$timescale
	1ns
$end
$scope module tb_shift_reg_siso $end
$var wire 1 ! sdo $end
$var reg 1 " clk $end
$var reg 1 # reset_n $end
$var reg 1 $ sdi $end
$scope module SISO0 $end
$var wire 1 " clk $end
$var wire 1 # reset_n $end
$var wire 1 $ sdi $end
$var wire 1 ! sdo $end
$var reg 4 % siso [3:0] $end
$upscope $end
$upscope $end
$enddefinitions $end
$comment Show the parameter values. $end
$dumpall
$end
#0
$dumpvars
b0 %
0$
0#
0"
0!
$end
#500
1"
#1000
0"
#1300
1$
1#
#1500
0$
1"
#2000
0"
#2500
b1 %
1$
1"
#3000
0"
#3500
b10 %
0$
1"
#4000
0"
#4500
b100 %
1"
#5000
0"
#5500
1!
b1000 %
1"
#6000
0"
#6500
0!
b0 %
1"
