Notes/UART/v1.0/src/baud_gen.sv
`timescale 1ns/1ps
/* 1. BAUD  GENERATOR

The baud genrator generates baud pulses. 
It either takes in the divisor from the firmware or uses the default one
Baud rate = 9600
clk 150Mhz
	
*/ 	

module mod_gen #(parameter int DIVISOR = 977)(
    input logic clk,
    input logic reset_n,
    output logic bpulse
);


logic [9:0] divisor;
logic [9:0] bclk_counter;

always_ff @(posedge clk) begin 
    if(!reset_n) begin 
        divisor <= DIVISOR;
        bclk_counter <= 10'd0;
        bpulse <= 1'b0;
    end else begin 
       bpulse <= 1'b0;
       if (bclk_counter == divisor -1'b1) begin 
            bclk_counter <= 10'd0;
            bpulse <= 1'b1;
       end
       else begin 
            bclk_counter <= bclk_counter +1'b1;
       end
    end
end


endmodule

Notes/UART/v1.0/tb/baud_gen_tb.sv
`timescale 1ns/1ps

module baud_gen_tb();
    logic clk;
    logic reset_n;
    logic bpulse;

    localparam int DIVISOR = 977;

    // Instantiate the uut

    mod_gen #(.DIVISOR(DIVISOR)) uut(
        .clk(clk),
        .reset_n(reset_n),
        .bpulse(bpulse)
    );

    /*
        1. Generate a clock signal with a period of 7.5 ns (150 MHz)
        
    */
    initial begin 
        clk = 1'b0;
        forever begin 
            #3.75 clk = ~clk;
            //$display("clk = %b", clk);
        end
    end

    /*
        2. :Generate an active low reset signal
        The reset signal is valid for 10 clock cycles
    */
    initial begin 
        $display("Asserting reset");
        reset_n = 1'b0;
        $display ("reset_n = %b", reset_n);
        repeat(10)@(posedge clk);
        $display("Deasserting reset");
        reset_n = 1'b1;
        $display ("reset_n = %b", reset_n);

        $display ("Running simulation for 2500 cycles");
        repeat(1500)@(posedge clk);

        reset_n = 1'b0;
        @(posedge clk);
        reset_n = 1'b1;
        repeat(1000)@(posedge clk);
        $finish;
    end
    
    /*
        Check if the the register is holding the count value 
    */

    logic [9:0] divisor;
    assign divisor = DIVISOR;
    initial begin 
        $display("DIVISOR = %d", divisor);
    end
       

    logic [9:0] bclk_counter;
    
    always @(posedge clk) begin 
        bclk_counter = uut.bclk_counter;
        if (!reset_n) begin 
            bclk_counter <= 10'd0;
            $display("Resetting bclk_counter to %d", bclk_counter);
        end else begin 
            $display("bclk_counter = %d", uut.bclk_counter);
            if (bclk_counter == divisor -1'b1) begin 
                $display("Baud pulse generated at time %t", $time);
            end
        end
    end

    initial begin 
        
        $dumpfile("baud_gen_tb.vcd");
        $dumpvars(0, baud_gen_tb);
        
    end
endmodule

Notes/UART/v1.0/baud_gen_tb.vcd
$date
	Wed Sep 30 08:25:27 2026
$end
$version
	Icarus Verilog
$end
$timescale
	1ps
$end
$scope module baud_gen_tb $end
$var wire 10 ! divisor [9:0] $end
$var wire 1 " bpulse $end
$var parameter 32 # DIVISOR $end
$var reg 10 $ bclk_counter [9:0] $end
$var reg 1 % clk $end
$var reg 1 & reset_n $end
$scope module uut $end
$var wire 1 % clk $end
$var wire 1 & reset_n $end
$var parameter 32 ' DIVISOR $end
$var reg 10 ( bclk_counter [9:0] $end
$var reg 1 " bpulse $end
$var reg 10 ) divisor [9:0] $end
$upscope $end
$upscope $end
$enddefinitions $end
$comment Show the parameter values. $end
$dumpall
b1111010001 '
b1111010001 #
$end
#0
$dumpvars
bx )
bx (
0&
0%
bx $
x"
b1111010001 !
$end
#3750
0"
b0 (
b1111010001 )
b0 $
1%
#7500
0%
#11250
1%
#15000
0%
#18750
1%
#22500
0%
#26250
1%
#30000
0%
#33750
1%
#37500
0%
#41250
1%
#45000
0%
#48750
1%
#52500
0%
#56250
1%
#60000
0%
#63750
1%
#67500
0%
#71250
1&
1%
#75000
0%
#78750
b1 (
1%
#82500
0%
#86250
b10 (
b1 $
1%
#90000
0%
#93750
b11 (
b10 $
1%
#97500
0%
#101250
b100 (
b11 $
1%
#105000
0%
#108750
b101 (
b100 $
1%
#112500
0%
#116250
b110 (
b101 $
1%
#120000
0%
#123750
b111 (
b110 $
1%
#127500
0%
#131250
b1000 (
b111 $
1%
#135000
0%
#138750
b1001 (
b1000 $
1%
#142500
0%
#146250
b1010 (
b1001 $
1%
#150000
0%
#153750
b1011 (
b1010 $
1%
#157500
0%
#161250
b1100 (
b1011 $
1%
#165000
0%
#168750
b1101 (
b1100 $
1%
#172500
0%
#176250
b1110 (
b1101 $
1%
#180000
0%
#183750
b1111 (
b1110 $
1%
#187500
0%
#191250
b10000 (
b1111 $
1%
#195000
0%
#198750
b10001 (
b10000 $
1%
#202500
0%
#206250
b10010 (
b10001 $
1%
#210000
0%
#213750
b10011 (
b10010 $
1%
#217500
0%
#221250
b10100 (
b10011 $
1%
#225000
0%
#228750
b10101 (
b10100 $
1%
#232500
0%
#236250
b10110 (
b10101 $
1%
#240000
0%
#243750
b10111 (
b10110 $
1%
#247500
0%
#251250
b11000 (
b10111 $
1%
#255000
0%
#258750
b11001 (
b11000 $
1%
#262500
0%
#266250
b11010 (
b11001 $
1%
#270000
0%
#273750
b11011 (
b11010 $
1%
#277500
0%
#281250
b11100 (
b11011 $
1%
#285000
0%
#288750
b11101 (
b11100 $
1%
#292500
0%
#296250
b11110 (
b11101 $
1%
#300000
0%
#303750
b11111 (
b11110 $
1%
#307500
0%
#311250
b100000 (
b11111 $
1%
#315000
0%
#318750
b100001 (
b100000 $
1%
#322500
0%
#326250
b100010 (
b100001 $
1%
#330000
0%
#333750
b100011 (
b100010 $
1%
#337500
0%
#341250
b100100 (
b100011 $
1%
#345000
0%
#348750
b100101 (
b100100 $
1%
#352500
0%
#356250
b100110 (
b100101 $
1%
#360000
0%
#363750
b100111 (
b100110 $
1%
#367500
0%
#371250
b101000 (
b100111 $
1%
#375000
0%
#378750
b101001 (
b101000 $
1%
#382500
0%
#386250
b101010 (
b101001 $
1%
#390000
0%
#393750
b101011 (
b101010 $
1%
#397500
0%
#401250
b101100 (
b101011 $
1%
#405000
0%
#408750
b101101 (
b101100 $
1%
#412500
0%
#416250
b101110 (
b101101 $
1%
#420000
0%
#423750
b101111 (
b101110 $
1%
#427500
0%
#431250
b110000 (
b101111 $
1%
#435000
0%
#438750
b110001 (
b110000 $
1%
#442500
0%
#446250
b110010 (
b110001 $
1%
#450000
0%
#453750
b110011 (
b110010 $
1%
#457500
0%
#461250
b110100 (
b110011 $
1%
#465000
0%
#468750
b110101 (
b110100 $
1%
#472500
0%
#476250
b110110 (
b110101 $
1%
#480000
0%
#483750
b110111 (
b110110 $
1%
#487500
0%
#491250
b111000 (
b110111 $
1%
#495000
0%
#498750
b111001 (
b111000 $
1%
#502500
0%
#506250
b111010 (
b111001 $
1%
#510000
0%
#513750
b111011 (
b111010 $
1%
#517500
0%
#521250
b111100 (
b111011 $
1%
#525000
0%
#528750
b111101 (
b111100 $
1%
#532500
0%
#536250
b111110 (
b111101 $
1%
#540000
0%
#543750
b111111 (
b111110 $
1%
#547500
0%
#551250
b1000000 (
b111111 $
1%
#555000
0%
#558750
b1000001 (
b1000000 $
1%
#562500
0%
#566250
b1000010 (
b1000001 $
1%
#570000
0%
#573750
b1000011 (
b1000010 $
1%
#577500
0%
#581250
b1000100 (
b1000011 $
1%
#585000
0%
#588750
b1000101 (
b1000100 $
1%
#592500
0%
#596250
b1000110 (
b1000101 $
1%
#600000
0%
#603750
b1000111 (
b1000110 $
1%
#607500
0%
#611250
b1001000 (
b1000111 $
1%
#615000
0%
#618750
b1001001 (
b1001000 $
1%
#622500
0%
#626250
b1001010 (
b1001001 $
1%
#630000
0%
#633750
b1001011 (
b1001010 $
1%
#637500
0%
#641250
b1001100 (
b1001011 $
1%
#645000
0%
#648750
b1001101 (
b1001100 $
1%
#652500
0%
#656250
b1001110 (
b1001101 $
1%
#660000
0%
#663750
b1001111 (
b1001110 $
1%
#667500
0%
#671250
b1010000 (
b1001111 $
1%
#675000
0%
#678750
b1010001 (
b1010000 $
1%
#682500
0%
#686250
b1010010 (
b1010001 $
1%
#690000
0%
#693750
b1010011 (
b1010010 $
1%
#697500
0%
#701250
b1010100 (
b1010011 $
1%
#705000
0%
#708750
b1010101 (
b1010100 $
1%
#712500
0%
#716250
b1010110 (
b1010101 $
1%
#720000
0%
#723750
b1010111 (
b1010110 $
1%
#727500
0%
#731250
b1011000 (
b1010111 $
1%
#735000
0%
#738750
b1011001 (
b1011000 $
1%
#742500
0%
#746250
b1011010 (
b1011001 $
1%
#750000
0%
#753750
b1011011 (
b1011010 $
1%
#757500
0%
#761250
b1011100 (
b1011011 $
1%
#765000
0%
#768750
b1011101 (
b1011100 $
1%
#772500
0%
#776250
b1011110 (
b1011101 $
1%
#780000
0%
#783750
b1011111 (
b1011110 $
1%
#787500
0%
#791250
b1100000 (
b1011111 $
1%
#795000
0%
#798750
b1100001 (
b1100000 $
1%
#802500
0%
#806250
b1100010 (
b1100001 $
1%
#810000
0%
#813750
b1100011 (
b1100010 $
1%
#817500
0%
#821250
b1100100 (
b1100011 $
1%
#825000
0%
#828750
b1100101 (
b1100100 $
1%
#832500
0%
#836250
b1100110 (
b1100101 $
1%
#840000
0%
#843750
b1100111 (
b1100110 $
1%
#847500
0%
#851250
b1101000 (
b1100111 $
1%
#855000
0%
#858750
b1101001 (
b1101000 $
1%
#862500
0%
#866250
b1101010 (
b1101001 $
1%
#870000
0%
#873750
b1101011 (
b1101010 $
1%
#877500
0%
#881250
b1101100 (
b1101011 $
1%
#885000
0%
#888750
b1101101 (
b1101100 $
1%
#892500
0%
#896250
b1101110 (
b1101101 $
1%
#900000
0%
#903750
b1101111 (
b1101110 $
1%
#907500
0%
#911250
b1110000 (
b1101111 $
1%
#915000
0%
#918750
b1110001 (
b1110000 $
1%
#922500
0%
#926250
b1110010 (
b1110001 $
1%
#930000
0%
#933750
b1110011 (
b1110010 $
1%
#937500
0%
#941250
b1110100 (
b1110011 $
1%
#945000
0%
#948750
b1110101 (
b1110100 $
1%
#952500
0%
#956250
b1110110 (
b1110101 $
1%
#960000
0%
#963750
b1110111 (
b1110110 $
1%
#967500
0%
#971250
b1111000 (
b1110111 $
1%
#975000
0%
#978750
b1111001 (
b1111000 $
1%
#982500
0%
#986250
b1111010 (
b1111001 $
1%
#990000
0%
#993750
b1111011 (
b1111010 $
1%
#997500
0%
#1001250
b1111100 (
b1111011 $
1%
#1005000
0%
#1008750
b1111101 (
b1111100 $
1%
#1012500
0%
#1016250
b1111110 (
b1111101 $
1%
#1020000
0%
#1023750
b1111111 (
b1111110 $
1%
#1027500
0%
#1031250
b10000000 (
b1111111 $
1%
#1035000
0%
#1038750
b10000001 (
b10000000 $
1%
#1042500
0%
#1046250
b10000010 (
b10000001 $
1%
#1050000
0%
#1053750
b10000011 (
b10000010 $
1%
#1057500
0%
#1061250
b10000100 (
b10000011 $
1%
#1065000
0%
#1068750
b10000101 (
b10000100 $
1%
#1072500
0%
#1076250
b10000110 (
b10000101 $
1%
#1080000
0%
#1083750
b10000111 (
b10000110 $
1%
#1087500
0%
#1091250
b10001000 (
b10000111 $
1%
#1095000
0%
#1098750
b10001001 (
b10001000 $
1%
#1102500
0%
#1106250
b10001010 (
b10001001 $
1%
#1110000
0%
#1113750
b10001011 (
b10001010 $
1%
#1117500
0%
#1121250
b10001100 (
b10001011 $
1%
#1125000
0%
#1128750
b10001101 (
b10001100 $
1%
#1132500
0%
#1136250
b10001110 (
b10001101 $
1%
#1140000
0%
#1143750
b10001111 (
b10001110 $
1%
#1147500
0%
#1151250
b10010000 (
b10001111 $
1%
#1155000
0%
#1158750
b10010001 (
b10010000 $
1%
#1162500
0%
#1166250
b10010010 (
b10010001 $
1%
#1170000
0%
#1173750
b10010011 (
b10010010 $
1%
#1177500
0%
#1181250
b10010100 (
b10010011 $
1%
#1185000
0%
#1188750
b10010101 (
b10010100 $
1%
#1192500
0%
#1196250
b10010110 (
b10010101 $
1%
#1200000
0%
#1203750
b10010111 (
b10010110 $
1%
#1207500
0%
#1211250
b10011000 (
b10010111 $
1%
#1215000
0%
#1218750
b10011001 (
b10011000 $
1%
#1222500
0%
#1226250
b10011010 (
b10011001 $
1%
#1230000
0%
#1233750
b10011011 (
b10011010 $
1%
#1237500
0%
#1241250
b10011100 (
b10011011 $
1%
#1245000
0%
#1248750
b10011101 (
b10011100 $
1%
#1252500
0%
#1256250
b10011110 (
b10011101 $
1%
#1260000
0%
#1263750
b10011111 (
b10011110 $
1%
#1267500
0%
#1271250
b10100000 (
b10011111 $
1%
#1275000
0%
#1278750
b10100001 (
b10100000 $
1%
#1282500
0%
#1286250
b10100010 (
b10100001 $
1%
#1290000
0%
#1293750
b10100011 (
b10100010 $
1%
#1297500
0%
#1301250
b10100100 (
b10100011 $
1%
#1305000
0%
#1308750
b10100101 (
b10100100 $
1%
#1312500
0%
#1316250
b10100110 (
b10100101 $
1%
#1320000
0%
#1323750
b10100111 (
b10100110 $
1%
#1327500
0%
#1331250
b10101000 (
b10100111 $
1%
#1335000
0%
#1338750
b10101001 (
b10101000 $
1%
#1342500
0%
#1346250
b10101010 (
b10101001 $
1%
#1350000
0%
#1353750
b10101011 (
b10101010 $
1%
#1357500
0%
#1361250
b10101100 (
b10101011 $
1%
#1365000
0%
#1368750
b10101101 (
b10101100 $
1%
#1372500
0%
#1376250
b10101110 (
b10101101 $
1%
#1380000
0%
#1383750
b10101111 (
b10101110 $
1%
#1387500
0%
#1391250
b10110000 (
b10101111 $
1%
#1395000
0%
#1398750
b10110001 (
b10110000 $
1%
#1402500
0%
#1406250
b10110010 (
b10110001 $
1%
#1410000
0%
#1413750
b10110011 (
b10110010 $
1%
#1417500
0%
#1421250
b10110100 (
b10110011 $
1%
#1425000
0%
#1428750
b10110101 (
b10110100 $
1%
#1432500
0%
#1436250
b10110110 (
b10110101 $
1%
#1440000
0%
#1443750
b10110111 (
b10110110 $
1%
#1447500
0%
#1451250
b10111000 (
b10110111 $
1%
#1455000
0%
#1458750
b10111001 (
b10111000 $
1%
#1462500
0%
#1466250
b10111010 (
b10111001 $
1%
#1470000
0%
#1473750
b10111011 (
b10111010 $
1%
#1477500
0%
#1481250
b10111100 (
b10111011 $
1%
#1485000
0%
#1488750
b10111101 (
b10111100 $
1%
#1492500
0%
#1496250
b10111110 (
b10111101 $
1%
#1500000
0%
#1503750
b10111111 (
b10111110 $
1%
#1507500
0%
#1511250
b11000000 (
b10111111 $
1%
#1515000
0%
#1518750
b11000001 (
b11000000 $
1%
#1522500
0%
#1526250
b11000010 (
b11000001 $
1%
#1530000
0%
#1533750
b11000011 (
b11000010 $
1%
#1537500
0%
#1541250
b11000100 (
b11000011 $
1%
#1545000
0%
#1548750
b11000101 (
b11000100 $
1%
#1552500
0%
#1556250
b11000110 (
b11000101 $
1%
#1560000
0%
#1563750
b11000111 (
b11000110 $
1%
#1567500
0%
#1571250
b11001000 (
b11000111 $
1%
#1575000
0%
#1578750
b11001001 (
b11001000 $
1%
#1582500
0%
#1586250
b11001010 (
b11001001 $
1%
#1590000
0%
#1593750
b11001011 (
b11001010 $
1%
#1597500
0%
#1601250
b11001100 (
b11001011 $
1%
#1605000
0%
#1608750
b11001101 (
b11001100 $
1%
#1612500
0%
#1616250
b11001110 (
b11001101 $
1%
#1620000
0%
#1623750
b11001111 (
b11001110 $
1%
#1627500
0%
#1631250
b11010000 (
b11001111 $
1%
#1635000
0%
#1638750
b11010001 (
b11010000 $
1%
#1642500
0%
#1646250
b11010010 (
b11010001 $
1%
#1650000
0%
#1653750
b11010011 (
b11010010 $
1%
#1657500
0%
#1661250
b11010100 (
b11010011 $
1%
#1665000
0%
#1668750
b11010101 (
b11010100 $
1%
#1672500
0%
#1676250
b11010110 (
b11010101 $
1%
#1680000
0%
#1683750
b11010111 (
b11010110 $
1%
#1687500
0%
#1691250
b11011000 (
b11010111 $
1%
#1695000
0%
#1698750
b11011001 (
b11011000 $
1%
#1702500
0%
#1706250
b11011010 (
b11011001 $
1%
#1710000
0%
#1713750
b11011011 (
b11011010 $
1%
#1717500
0%
#1721250
b11011100 (
b11011011 $
1%
#1725000
0%
#1728750
b11011101 (
b11011100 $
1%
#1732500
0%
#1736250
b11011110 (
b11011101 $
1%
#1740000
0%
#1743750
b11011111 (
b11011110 $
1%
#1747500
0%
#1751250
b11100000 (
b11011111 $
1%
#1755000
0%
#1758750
b11100001 (
b11100000 $
1%
#1762500
0%
#1766250
b11100010 (
b11100001 $
1%
#1770000
0%
#1773750
b11100011 (
b11100010 $
1%
#1777500
0%
#1781250
b11100100 (
b11100011 $
1%
#1785000
0%
#1788750
b11100101 (
b11100100 $
1%
#1792500
0%
#1796250
b11100110 (
b11100101 $
1%
#1800000
0%
#1803750
b11100111 (
b11100110 $
1%
#1807500
0%
#1811250
b11101000 (
b11100111 $
1%
#1815000
0%
#1818750
b11101001 (
b11101000 $
1%
#1822500
0%
#1826250
b11101010 (
b11101001 $
1%
#1830000
0%
#1833750
b11101011 (
b11101010 $
1%
#1837500
0%
#1841250
b11101100 (
b11101011 $
1%
#1845000
0%
#1848750
b11101101 (
b11101100 $
1%
#1852500
0%
#1856250
b11101110 (
b11101101 $
1%
#1860000
0%
#1863750
b11101111 (
b11101110 $
1%
#1867500
0%
#1871250
b11110000 (
b11101111 $
1%
#1875000
0%
#1878750
b11110001 (
b11110000 $
1%
#1882500
0%
#1886250
b11110010 (
b11110001 $
1%
#1890000
0%
#1893750
b11110011 (
b11110010 $
1%
#1897500
0%
#1901250
b11110100 (
b11110011 $
1%
#1905000
0%
#1908750
b11110101 (
b11110100 $
1%
#1912500
0%
#1916250
b11110110 (
b11110101 $
1%
#1920000
0%
#1923750
b11110111 (
b11110110 $
1%
#1927500
0%
#1931250
b11111000 (
b11110111 $
1%
#1935000
0%
#1938750
b11111001 (
b11111000 $
1%
#1942500
0%
#1946250
b11111010 (
b11111001 $
1%
#1950000
0%
#1953750
b11111011 (
b11111010 $
1%
#1957500
0%
#1961250
b11111100 (
b11111011 $
1%
#1965000
0%
#1968750
b11111101 (
b11111100 $
1%
#1972500
0%
#1976250
b11111110 (
b11111101 $
1%
#1980000
0%
#1983750
b11111111 (
b11111110 $
1%
#1987500
0%
#1991250
b100000000 (
b11111111 $
1%
#1995000
0%
#1998750
b100000001 (
b100000000 $
1%
#2002500
0%
#2006250
b100000010 (
b100000001 $
1%
#2010000
0%
#2013750
b100000011 (
b100000010 $
1%
#2017500
0%
#2021250
b100000100 (
b100000011 $
1%
#2025000
0%
#2028750
b100000101 (
b100000100 $
1%
#2032500
0%
#2036250
b100000110 (
b100000101 $
1%
#2040000
0%
#2043750
b100000111 (
b100000110 $
1%
#2047500
0%
#2051250
b100001000 (
b100000111 $
1%
#2055000
0%
#2058750
b100001001 (
b100001000 $
1%
#2062500
0%
#2066250
b100001010 (
b100001001 $
1%
#2070000
0%
#2073750
b100001011 (
b100001010 $
1%
#2077500
0%
#2081250
b100001100 (
b100001011 $
1%
#2085000
0%
#2088750
b100001101 (
b100001100 $
1%
#2092500
0%
#2096250
b100001110 (
b100001101 $
1%
#2100000
0%
#2103750
b100001111 (
b100001110 $
1%
#2107500
0%
#2111250
b100010000 (
b100001111 $
1%
#2115000
0%
#2118750
b100010001 (
b100010000 $
1%
#2122500
0%
#2126250
b100010010 (
b100010001 $
1%
#2130000
0%
#2133750
b100010011 (
b100010010 $
1%
#2137500
0%
#2141250
b100010100 (
b100010011 $
1%
#2145000
0%
#2148750
b100010101 (
b100010100 $
1%
#2152500
0%
#2156250
b100010110 (
b100010101 $
1%
#2160000
0%
#2163750
b100010111 (
b100010110 $
1%
#2167500
0%
#2171250
b100011000 (
b100010111 $
1%
#2175000
0%
#2178750
b100011001 (
b100011000 $
1%
#2182500
0%
#2186250
b100011010 (
b100011001 $
1%
#2190000
0%
#2193750
b100011011 (
b100011010 $
1%
#2197500
0%
#2201250
b100011100 (
b100011011 $
1%
#2205000
0%
#2208750
b100011101 (
b100011100 $
1%
#2212500
0%
#2216250
b100011110 (
b100011101 $
1%
#2220000
0%
#2223750
b100011111 (
b100011110 $
1%
#2227500
0%
#2231250
b100100000 (
b100011111 $
1%
#2235000
0%
#2238750
b100100001 (
b100100000 $
1%
#2242500
0%
#2246250
b100100010 (
b100100001 $
1%
#2250000
0%
#2253750
b100100011 (
b100100010 $
1%
#2257500
0%
#2261250
b100100100 (
b100100011 $
1%
#2265000
0%
#2268750
b100100101 (
b100100100 $
1%
#2272500
0%
#2276250
b100100110 (
b100100101 $
1%
#2280000
0%
#2283750
b100100111 (
b100100110 $
1%
#2287500
0%
#2291250
b100101000 (
b100100111 $
1%
#2295000
0%
#2298750
b100101001 (
b100101000 $
1%
#2302500
0%
#2306250
b100101010 (
b100101001 $
1%
#2310000
0%
#2313750
b100101011 (
b100101010 $
1%
#2317500
0%
#2321250
b100101100 (
b100101011 $
1%
#2325000
0%
#2328750
b100101101 (
b100101100 $
1%
#2332500
0%
#2336250
b100101110 (
b100101101 $
1%
#2340000
0%
#2343750
b100101111 (
b100101110 $
1%
#2347500
0%
#2351250
b100110000 (
b100101111 $
1%
#2355000
0%
#2358750
b100110001 (
b100110000 $
1%
#2362500
0%
#2366250
b100110010 (
b100110001 $
1%
#2370000
0%
#2373750
b100110011 (
b100110010 $
1%
#2377500
0%
#2381250
b100110100 (
b100110011 $
1%
#2385000
0%
#2388750
b100110101 (
b100110100 $
1%
#2392500
0%
#2396250
b100110110 (
b100110101 $
1%
#2400000
0%
#2403750
b100110111 (
b100110110 $
1%
#2407500
0%
#2411250
b100111000 (
b100110111 $
1%
#2415000
0%
#2418750
b100111001 (
b100111000 $
1%
#2422500
0%
#2426250
b100111010 (
b100111001 $
1%
#2430000
0%
#2433750
b100111011 (
b100111010 $
1%
#2437500
0%
#2441250
b100111100 (
b100111011 $
1%
#2445000
0%
#2448750
b100111101 (
b100111100 $
1%
#2452500
0%
#2456250
b100111110 (
b100111101 $
1%
#2460000
0%
#2463750
b100111111 (
b100111110 $
1%
#2467500
0%
#2471250
b101000000 (
b100111111 $
1%
#2475000
0%
#2478750
b101000001 (
b101000000 $
1%
#2482500
0%
#2486250
b101000010 (
b101000001 $
1%
#2490000
0%
#2493750
b101000011 (
b101000010 $
1%
#2497500
0%
#2501250
b101000100 (
b101000011 $
1%
#2505000
0%
#2508750
b101000101 (
b101000100 $
1%
#2512500
0%
#2516250
b101000110 (
b101000101 $
1%
#2520000
0%
#2523750
b101000111 (
b101000110 $
1%
#2527500
0%
#2531250
b101001000 (
b101000111 $
1%
#2535000
0%
#2538750
b101001001 (
b101001000 $
1%
#2542500
0%
#2546250
b101001010 (
b101001001 $
1%
#2550000
0%
#2553750
b101001011 (
b101001010 $
1%
#2557500
0%
#2561250
b101001100 (
b101001011 $
1%
#2565000
0%
#2568750
b101001101 (
b101001100 $
1%
#2572500
0%
#2576250
b101001110 (
b101001101 $
1%
#2580000
0%
#2583750
b101001111 (
b101001110 $
1%
#2587500
0%
#2591250
b101010000 (
b101001111 $
1%
#2595000
0%
#2598750
b101010001 (
b101010000 $
1%
#2602500
0%
#2606250
b101010010 (
b101010001 $
1%
#2610000
0%
#2613750
b101010011 (
b101010010 $
1%
#2617500
0%
#2621250
b101010100 (
b101010011 $
1%
#2625000
0%
#2628750
b101010101 (
b101010100 $
1%
#2632500
0%
#2636250
b101010110 (
b101010101 $
1%
#2640000
0%
#2643750
b101010111 (
b101010110 $
1%
#2647500
0%
#2651250
b101011000 (
b101010111 $
1%
#2655000
0%
#2658750
b101011001 (
b101011000 $
1%
#2662500
0%
#2666250
b101011010 (
b101011001 $
1%
#2670000
0%
#2673750
b101011011 (
b101011010 $
1%
#2677500
0%
#2681250
b101011100 (
b101011011 $
1%
#2685000
0%
#2688750
b101011101 (
b101011100 $
1%
#2692500
0%
#2696250
b101011110 (
b101011101 $
1%
#2700000
0%
#2703750
b101011111 (
b101011110 $
1%
#2707500
0%
#2711250
b101100000 (
b101011111 $
1%
#2715000
0%
#2718750
b101100001 (
b101100000 $
1%
#2722500
0%
#2726250
b101100010 (
b101100001 $
1%
#2730000
0%
#2733750
b101100011 (
b101100010 $
1%
#2737500
0%
#2741250
b101100100 (
b101100011 $
1%
#2745000
0%
#2748750
b101100101 (
b101100100 $
1%
#2752500
0%
#2756250
b101100110 (
b101100101 $
1%
#2760000
0%
#2763750
b101100111 (
b101100110 $
1%
#2767500
0%
#2771250
b101101000 (
b101100111 $
1%
#2775000
0%
#2778750
b101101001 (
b101101000 $
1%
#2782500
0%
#2786250
b101101010 (
b101101001 $
1%
#2790000
0%
#2793750
b101101011 (
b101101010 $
1%
#2797500
0%
#2801250
b101101100 (
b101101011 $
1%
#2805000
0%
#2808750
b101101101 (
b101101100 $
1%
#2812500
0%
#2816250
b101101110 (
b101101101 $
1%
#2820000
0%
#2823750
b101101111 (
b101101110 $
1%
#2827500
0%
#2831250
b101110000 (
b101101111 $
1%
#2835000
0%
#2838750
b101110001 (
b101110000 $
1%
#2842500
0%
#2846250
b101110010 (
b101110001 $
1%
#2850000
0%
#2853750
b101110011 (
b101110010 $
1%
#2857500
0%
#2861250
b101110100 (
b101110011 $
1%
#2865000
0%
#2868750
b101110101 (
b101110100 $
1%
#2872500
0%
#2876250
b101110110 (
b101110101 $
1%
#2880000
0%
#2883750
b101110111 (
b101110110 $
1%
#2887500
0%
#2891250
b101111000 (
b101110111 $
1%
#2895000
0%
#2898750
b101111001 (
b101111000 $
1%
#2902500
0%
#2906250
b101111010 (
b101111001 $
1%
#2910000
0%
#2913750
b101111011 (
b101111010 $
1%
#2917500
0%
#2921250
b101111100 (
b101111011 $
1%
#2925000
0%
#2928750
b101111101 (
b101111100 $
1%
#2932500
0%
#2936250
b101111110 (
b101111101 $
1%
#2940000
0%
#2943750
b101111111 (
b101111110 $
1%
#2947500
0%
#2951250
b110000000 (
b101111111 $
1%
#2955000
0%
#2958750
b110000001 (
b110000000 $
1%
#2962500
0%
#2966250
b110000010 (
b110000001 $
1%
#2970000
0%
#2973750
b110000011 (
b110000010 $
1%
#2977500
0%
#2981250
b110000100 (
b110000011 $
1%
#2985000
0%
#2988750
b110000101 (
b110000100 $
1%
#2992500
0%
#2996250
b110000110 (
b110000101 $
1%
#3000000
0%
#3003750
b110000111 (
b110000110 $
1%
#3007500
0%
#3011250
b110001000 (
b110000111 $
1%
#3015000
0%
#3018750
b110001001 (
b110001000 $
1%
#3022500
0%
#3026250
b110001010 (
b110001001 $
1%
#3030000
0%
#3033750
b110001011 (
b110001010 $
1%
#3037500
0%
#3041250
b110001100 (
b110001011 $
1%
#3045000
0%
#3048750
b110001101 (
b110001100 $
1%
#3052500
0%
#3056250
b110001110 (
b110001101 $
1%
#3060000
0%
#3063750
b110001111 (
b110001110 $
1%
#3067500
0%
#3071250
b110010000 (
b110001111 $
1%
#3075000
0%
#3078750
b110010001 (
b110010000 $
1%
#3082500
0%
#3086250
b110010010 (
b110010001 $
1%
#3090000
0%
#3093750
b110010011 (
b110010010 $
1%
#3097500
0%
#3101250
b110010100 (
b110010011 $
1%
#3105000
0%
#3108750
b110010101 (
b110010100 $
1%
#3112500
0%
#3116250
b110010110 (
b110010101 $
1%
#3120000
0%
#3123750
b110010111 (
b110010110 $
1%
#3127500
0%
#3131250
b110011000 (
b110010111 $
1%
#3135000
0%
#3138750
b110011001 (
b110011000 $
1%
#3142500
0%
#3146250
b110011010 (
b110011001 $
1%
#3150000
0%
#3153750
b110011011 (
b110011010 $
1%
#3157500
0%
#3161250
b110011100 (
b110011011 $
1%
#3165000
0%
#3168750
b110011101 (
b110011100 $
1%
#3172500
0%
#3176250
b110011110 (
b110011101 $
1%
#3180000
0%
#3183750
b110011111 (
b110011110 $
1%
#3187500
0%
#3191250
b110100000 (
b110011111 $
1%
#3195000
0%
#3198750
b110100001 (
b110100000 $
1%
#3202500
0%
#3206250
b110100010 (
b110100001 $
1%
#3210000
0%
#3213750
b110100011 (
b110100010 $
1%
#3217500
0%
#3221250
b110100100 (
b110100011 $
1%
#3225000
0%
#3228750
b110100101 (
b110100100 $
1%
#3232500
0%
#3236250
b110100110 (
b110100101 $
1%
#3240000
0%
#3243750
b110100111 (
b110100110 $
1%
#3247500
0%
#3251250
b110101000 (
b110100111 $
1%
#3255000
0%
#3258750
b110101001 (
b110101000 $
1%
#3262500
0%
#3266250
b110101010 (
b110101001 $
1%
#3270000
0%
#3273750
b110101011 (
b110101010 $
1%
#3277500
0%
#3281250
b110101100 (
b110101011 $
1%
#3285000
0%
#3288750
b110101101 (
b110101100 $
1%
#3292500
0%
#3296250
b110101110 (
b110101101 $
1%
#3300000
0%
#3303750
b110101111 (
b110101110 $
1%
#3307500
0%
#3311250
b110110000 (
b110101111 $
1%
#3315000
0%
#3318750
b110110001 (
b110110000 $
1%
#3322500
0%
#3326250
b110110010 (
b110110001 $
1%
#3330000
0%
#3333750
b110110011 (
b110110010 $
1%
#3337500
0%
#3341250
b110110100 (
b110110011 $
1%
#3345000
0%
#3348750
b110110101 (
b110110100 $
1%
#3352500
0%
#3356250
b110110110 (
b110110101 $
1%
#3360000
0%
#3363750
b110110111 (
b110110110 $
1%
#3367500
0%
#3371250
b110111000 (
b110110111 $
1%
#3375000
0%
#3378750
b110111001 (
b110111000 $
1%
#3382500
0%
#3386250
b110111010 (
b110111001 $
1%
#3390000
0%
#3393750
b110111011 (
b110111010 $
1%
#3397500
0%
#3401250
b110111100 (
b110111011 $
1%
#3405000
0%
#3408750
b110111101 (
b110111100 $
1%
#3412500
0%
#3416250
b110111110 (
b110111101 $
1%
#3420000
0%
#3423750
b110111111 (
b110111110 $
1%
#3427500
0%
#3431250
b111000000 (
b110111111 $
1%
#3435000
0%
#3438750
b111000001 (
b111000000 $
1%
#3442500
0%
#3446250
b111000010 (
b111000001 $
1%
#3450000
0%
#3453750
b111000011 (
b111000010 $
1%
#3457500
0%
#3461250
b111000100 (
b111000011 $
1%
#3465000
0%
