sequentialCircuits/shift_regs/sipo/sipo.v
module sipo (
    input serial_data_in,
    input clk,
    input rst_n,
    output reg [3:0] q
);

    always@(posedge clk) begin
        if (!rst_n)
            q <= 4'b0000;
        else
            q[3:0]<= {q[2:0],serial_data_in};
    end

endmodule

sequentialCircuits/shift_regs/sipo/sipo_tb.v
module sipo_tb();
    reg reset_n;
    reg clk=0;
    reg d;
    wire [3:0]q;
    integer i;
    reg [1:0] delay;
    
    sipo uut (
        .clk(clk),
        .rst_n (reset_n),
        .serial_data_in (d),
        .q(q)
    );

    always begin 
        #0.5 clk = ~clk;
    end

    initial begin
        reset_n = 0; d =0;
        for (i=0;i<4;i++) begin
            delay = $urandom_range(1,3);
            #(delay) d = ~d;
        end
        reset_n = 1; 
        for (i=0;i<4;i++) begin
            delay = $urandom_range(1,3);
            #(delay) d = ~d;
        end

    end

    initial begin
        $dumpfile("wave.vcd");
        $dumpvars(0,sipo_tb);
        #40 $finish;

    end 

endmodule

sequentialCircuits/shift_regs/sipo/wave.vcd
$date
	Sun Jul 13 12:23:43 2025
$end
$version
	Icarus Verilog
$end
$timescale
	1s
$end
$scope module sipo_tb $end
$var wire 4 ! q [3:0] $end
$var reg 1 " clk $end
$var reg 1 # d $end
$var reg 2 $ delay [1:0] $end
$var reg 1 % reset_n $end
$var integer 32 & i [31:0] $end
$scope module uut $end
$var wire 1 " clk $end
$var wire 1 % rst_n $end
$var wire 1 # serial_data_in $end
$var reg 4 ' q [3:0] $end
$upscope $end
$upscope $end
$enddefinitions $end
$comment Show the parameter values. $end
$dumpall
$end
#0
$dumpvars
bx '
b0 &
0%
b10 $
0#
0"
bx !
$end
#1
b0 !
b0 '
1"
#2
0"
b1 $
b1 &
1#
#3
1"
b10 &
0#
#4
0"
b11 &
1#
#5
1"
b10 $
1%
b0 &
0#
#6
0"
#7
b1 !
b1 '
1"
b11 $
b1 &
1#
#8
0"
#9
b11 !
b11 '
1"
#10
0"
b1 $
b10 &
0#
#11
b111 !
b111 '
1"
b11 &
1#
#12
0"
b100 &
0#
#13
b1110 !
b1110 '
1"
#14
0"
#15
b1100 !
b1100 '
1"
#16
0"
#17
b1000 !
b1000 '
1"
#18
0"
#19
b0 !
b0 '
1"
